etc/lssh.conf
lssh-0.2.1.data/data/share/doc/lssh/README.md
lssh-0.2.1.data/scripts/lssh
lssh-0.2.1.dist-info/DESCRIPTION.rst
lssh-0.2.1.dist-info/METADATA
lssh-0.2.1.dist-info/RECORD
lssh-0.2.1.dist-info/WHEEL
lssh-0.2.1.dist-info/metadata.json
lssh-0.2.1.dist-info/top_level.txt
src/__init__.py
src/checkconfig.py
src/checkconfigdb.py
src/constants.py
src/lssh.py
src/sec.py
src/utils.py
src/variables.py
src/builtins/__init__.py
src/builtins/cd.py
src/builtins/exit.py
src/builtins/vim.py
